autolv/__init__.py
autolv/datatypes.py
autolv/interface.py
autolv/vistrings.py
autolv-1.0.6.dist-info/LICENSE
autolv-1.0.6.dist-info/METADATA
autolv-1.0.6.dist-info/WHEEL
autolv-1.0.6.dist-info/top_level.txt
autolv-1.0.6.dist-info/RECORD
