Metadata-Version: 2.1
Name: autolv
Version: 1.0.6
Summary: Automate LabVIEW from Python
Home-page: https://github.com/l-johnston/autolv
Author: Lee Johnston
Author-email: lee.johnston.100@gmail.com
Project-URL: Bug Tracker, https://github.com/l-johnston/autolv/issues
Platform: Windows
Requires-Python: >=3.8
License-File: LICENSE
Requires-Dist: pywin32
Requires-Dist: numpy
